vimanga/__init__.py
vimanga/__main__.py
vimanga/cli.py
vimanga/utils.py
vimanga/api/__init__.py
vimanga/api/constants.py
vimanga/api/core.py
vimanga/api/types.py
vimanga-0.2.1.dist-info/DESCRIPTION.rst
vimanga-0.2.1.dist-info/METADATA
vimanga-0.2.1.dist-info/RECORD
vimanga-0.2.1.dist-info/WHEEL
vimanga-0.2.1.dist-info/entry_points.txt
vimanga-0.2.1.dist-info/metadata.json
vimanga-0.2.1.dist-info/top_level.txt
