Metadata-Version: 2.0
Name: vimanga
Version: 0.2.1
Summary: App for download manga
Home-page: https://github.com/akhail/vimanga
Author: Michel Betancourt
Author-email: MichelBetancourt23@gmail.com
License: MIT license
Keywords: vimanga
Platform: UNKNOWN
Classifier: Development Status :: 2 - Pre-Alpha
Classifier: License :: OSI Approved :: MIT License
Classifier: Natural Language :: English
Classifier: Programming Language :: Python :: 3
Classifier: Programming Language :: Python :: 3.5
Classifier: Programming Language :: Python :: 3.6
Requires-Dist: tebless
Requires-Dist: reportlab
Requires-Dist: requests
Requires-Dist: tqdm
Requires-Dist: fire
